tifonts/__init__.py
tifonts/font_loader.py
tifonts/text_renderer.py
tifonts-0.1.0.dist-info/licenses/LICENSE
tifonts-0.1.0.dist-info/METADATA
tifonts-0.1.0.dist-info/WHEEL
tifonts-0.1.0.dist-info/top_level.txt
tifonts-0.1.0.dist-info/RECORD
