Metadata-Version: 2.4
Name: tifonts
Version: 0.1.0
Summary: a Python library designed to render pixel-based fonts within the `taichi-lang` environment. It allows users to display text on a Taichi canvas with customizable fonts, sizes, colors, and positions.
Requires-Python: >=3.12
License-File: LICENSE
Requires-Dist: numpy>=2.3.3
Requires-Dist: taichi>=1.7.4
Requires-Dist: sphinx
Requires-Dist: sphinx-rtd-theme
Requires-Dist: sphinx-autodoc-typehints
Requires-Dist: twine>=6.2.0
Requires-Dist: build>=1.3.0
Dynamic: license-file
